lab03/lab03/adders.v
`timescale 1ns / 1ps

module half_adder(
    input a,
    input b,
    output sum,
    output carry
);
    assign sum = a ^ b;
    assign carry = a & b;
endmodule

module full_adder(
    input a,
    input b,
    input cin,
    output sum,
    output cout
);
    assign sum = a ^ b ^ cin;
    assign cout = (a & b) | (a & cin) | (b & cin);
endmodule

module adder_4bit(
    input [3:0] a,
    input [3:0] b,
    input cin,
    output [3:0] sum,
    output cout
);
    wire c1;
    wire c2;
    wire c3;

    full_adder fa0 (.a(a[0]), .b(b[0]), .cin(cin), .sum(sum[0]), .cout(c1));
    full_adder fa1 (.a(a[1]), .b(b[1]), .cin(c1), .sum(sum[1]), .cout(c2));
    full_adder fa2 (.a(a[2]), .b(b[2]), .cin(c2), .sum(sum[2]), .cout(c3));
    full_adder fa3 (.a(a[3]), .b(b[3]), .cin(c3), .sum(sum[3]), .cout(cout));
endmodule

lab03/lab03/tb_adders.v
`timescale 1ns / 1ps

module tb_adders;
    reg a;
    reg b;
    reg cin;
    wire ha_sum;
    wire ha_carry;
    wire sum;
    wire cout;

    reg [3:0] a4;
    reg [3:0] b4;
    reg cin4;
    wire [3:0] sum4;
    wire cout4;

    integer i;

    half_adder ha (.a(a), .b(b), .sum(ha_sum), .carry(ha_carry));
    full_adder fa (.a(a), .b(b), .cin(cin), .sum(sum), .cout(cout));
    adder_4bit add4 (.a(a4), .b(b4), .cin(cin4), .sum(sum4), .cout(cout4));

    initial begin
        $dumpfile("lab03_adders.vcd");
        $dumpvars(0, tb_adders);

        $display("Full adder truth table");
        $display("a b cin | sum cout");

        for (i = 0; i < 8; i = i + 1) begin
            {a, b, cin} = i[2:0];
            #10;
            $display("%b %b  %b  |  %b    %b", a, b, cin, sum, cout);
        end

        $display("4-bit adder checks");
        a4 = 4'd3;  b4 = 4'd5;  cin4 = 1'b0; #10;
        $display("%d + %d + %d = %d carry=%b", a4, b4, cin4, sum4, cout4);

        a4 = 4'd9;  b4 = 4'd7;  cin4 = 1'b0; #10;
        $display("%d + %d + %d = %d carry=%b", a4, b4, cin4, sum4, cout4);

        a4 = 4'd15; b4 = 4'd15; cin4 = 1'b1; #10;
        $display("%d + %d + %d = %d carry=%b", a4, b4, cin4, sum4, cout4);

        $finish;
    end
endmodule

lab03/lab03/lab03_adders.vcd
$date
	Sun May 17 22:59:28 2026
$end
$version
	Icarus Verilog
$end
$timescale
	1ps
$end
$scope module tb_adders $end
$var wire 4 ! sum4 [3:0] $end
$var wire 1 " sum $end
$var wire 1 # ha_sum $end
$var wire 1 $ ha_carry $end
$var wire 1 % cout4 $end
$var wire 1 & cout $end
$var reg 1 ' a $end
$var reg 4 ( a4 [3:0] $end
$var reg 1 ) b $end
$var reg 4 * b4 [3:0] $end
$var reg 1 + cin $end
$var reg 1 , cin4 $end
$var integer 32 - i [31:0] $end
$scope module add4 $end
$var wire 4 . a [3:0] $end
$var wire 4 / b [3:0] $end
$var wire 1 , cin $end
$var wire 4 0 sum [3:0] $end
$var wire 1 % cout $end
$var wire 1 1 c3 $end
$var wire 1 2 c2 $end
$var wire 1 3 c1 $end
$scope module fa0 $end
$var wire 1 4 a $end
$var wire 1 5 b $end
$var wire 1 , cin $end
$var wire 1 3 cout $end
$var wire 1 6 sum $end
$upscope $end
$scope module fa1 $end
$var wire 1 7 a $end
$var wire 1 8 b $end
$var wire 1 3 cin $end
$var wire 1 2 cout $end
$var wire 1 9 sum $end
$upscope $end
$scope module fa2 $end
$var wire 1 : a $end
$var wire 1 ; b $end
$var wire 1 2 cin $end
$var wire 1 1 cout $end
$var wire 1 < sum $end
$upscope $end
$scope module fa3 $end
$var wire 1 = a $end
$var wire 1 > b $end
$var wire 1 1 cin $end
$var wire 1 % cout $end
$var wire 1 ? sum $end
$upscope $end
$upscope $end
$scope module fa $end
$var wire 1 ' a $end
$var wire 1 ) b $end
$var wire 1 + cin $end
$var wire 1 & cout $end
$var wire 1 " sum $end
$upscope $end
$scope module ha $end
$var wire 1 ' a $end
$var wire 1 ) b $end
$var wire 1 $ carry $end
$var wire 1 # sum $end
$upscope $end
$upscope $end
$enddefinitions $end
$comment Show the parameter values. $end
$dumpall
$end
#0
$dumpvars
x?
x>
x=
x<
x;
x:
x9
x8
x7
x6
x5
x4
x3
x2
x1
bx 0
bx /
bx .
b0 -
x,
0+
bx *
0)
bx (
0'
0&
x%
0$
0#
0"
bx !
$end
#10000
1"
1+
b1 -
#20000
1#
1"
1)
0+
b10 -
#30000
1&
0"
1+
b11 -
#40000
0&
1"
1'
0)
0+
b100 -
#50000
1&
0"
1+
b101 -
#60000
0#
1$
0"
1)
0+
b110 -
#70000
1"
1+
b111 -
#80000
1?
11
0<
12
09
b1000 !
b1000 0
13
0%
06
15
08
1;
0>
14
17
0:
0=
0,
b101 *
b101 /
b11 (
b11 .
b1000 -
#90000
b0 !
b0 0
1%
0?
18
07
1=
b111 *
b111 /
b1001 (
b1001 .
#100000
1?
19
1<
b1111 !
b1111 0
16
1>
17
1:
1,
b1111 *
b1111 /
b1111 (
b1111 .
