lab10 (1)/lab10/traffic_light_controller.v
`timescale 1ns / 1ps

module traffic_light_controller(
    input clk,
    input reset,
    input ped_request,
    input school_zone_active,
    output reg [2:0] main_light,
    output reg [2:0] side_light,
    output reg walk_light
);

    localparam RED   = 3'b100;
    localparam YELLOW = 3'b010;
    localparam GREEN  = 3'b001;

    localparam [1:0] S_MAIN_GREEN  = 2'b00;
    localparam [1:0] S_MAIN_YELLOW = 2'b01;
    localparam [1:0] S_SIDE_GREEN  = 2'b10;
    localparam [1:0] S_SIDE_YELLOW = 2'b11;

    localparam [4:0] MG_NORMAL  = 5'd20;
    localparam [4:0] MG_PED     = 5'd5;
    localparam [4:0] MG_SCHOOL  = 5'd6;
    localparam [4:0] YLW_TICKS  = 5'd4;
    localparam [4:0] SG_NORMAL  = 5'd10;
    localparam [4:0] SG_SCHOOL  = 5'd14;

    reg [1:0] state;
    reg [4:0] timer;
    reg [4:0] limit;

    always @(*) begin
        case (state)
            S_MAIN_GREEN: begin
                main_light = GREEN;
                side_light = RED;
                walk_light = 1'b0;
                if (school_zone_active)
                    limit = MG_SCHOOL;
                else if (ped_request)
                    limit = MG_PED;
                else
                    limit = MG_NORMAL;
            end
            S_MAIN_YELLOW: begin
                main_light = YELLOW;
                side_light = RED;
                walk_light = 1'b0;
                limit = YLW_TICKS;
            end
            S_SIDE_GREEN: begin
                main_light = RED;
                side_light = GREEN;
                walk_light = 1'b1;
                if (school_zone_active)
                    limit = SG_SCHOOL;
                else
                    limit = SG_NORMAL;
            end
            S_SIDE_YELLOW: begin
                main_light = RED;
                side_light = YELLOW;
                walk_light = 1'b0;
                limit = YLW_TICKS;
            end
            default: begin
                main_light = GREEN;
                side_light = RED;
                walk_light = 1'b0;
                limit = MG_NORMAL;
            end
        endcase
    end

    always @(posedge clk or posedge reset) begin
        if (reset) begin
            state <= S_MAIN_GREEN;
            timer <= 5'd0;
        end else if (timer >= limit - 5'd1) begin
            timer <= 5'd0;
            case (state)
                S_MAIN_GREEN:  state <= S_MAIN_YELLOW;
                S_MAIN_YELLOW: state <= S_SIDE_GREEN;
                S_SIDE_GREEN:  state <= S_SIDE_YELLOW;
                S_SIDE_YELLOW: state <= S_MAIN_GREEN;
                default:       state <= S_MAIN_GREEN;
            endcase
        end else begin
            timer <= timer + 5'd1;
        end
    end

endmodule

lab10 (1)/lab10/tb_traffic_light_controller.v
`timescale 1ns / 1ps

module tb_traffic_light_controller;

    reg clk;
    reg reset;
    reg ped_request;
    reg school_zone_active;
    wire [2:0] main_light;
    wire [2:0] side_light;
    wire walk_light;

    traffic_light_controller uut (
        .clk(clk),
        .reset(reset),
        .ped_request(ped_request),
        .school_zone_active(school_zone_active),
        .main_light(main_light),
        .side_light(side_light),
        .walk_light(walk_light)
    );

    initial begin
        clk = 1'b0;
        forever #5 clk = ~clk;
    end

    initial begin
        $dumpfile("lab10_traffic_light.vcd");
        $dumpvars(0, tb_traffic_light_controller);

        reset = 1'b1;
        ped_request = 1'b0;
        school_zone_active = 1'b0;
        #12;

        reset = 1'b0;
        #90;

        ped_request = 1'b1;
        #40;

        ped_request = 1'b0;
        #100;

        reset = 1'b1;
        #10;

        reset = 1'b0;
        #40;

        $finish;
    end

endmodule

lab10 (1)/lab10/lab10_traffic_light.vcd
$date
	Mon Jul 20 15:05:18 2026
$end
$version
	Icarus Verilog
$end
$timescale
	1ps
$end
$scope module tb_traffic_light_controller $end
$var wire 1 ! walk_light $end
$var wire 3 " side_light [2:0] $end
$var wire 3 # main_light [2:0] $end
$var reg 1 $ clk $end
$var reg 1 % ped_request $end
$var reg 1 & reset $end
$var reg 1 ' school_zone_active $end
$scope module uut $end
$var wire 1 $ clk $end
$var wire 1 % ped_request $end
$var wire 1 & reset $end
$var wire 1 ' school_zone_active $end
$var parameter 3 ( GREEN $end
$var parameter 5 ) MG_NORMAL $end
$var parameter 5 * MG_PED $end
$var parameter 5 + MG_SCHOOL $end
$var parameter 3 , RED $end
$var parameter 5 - SG_NORMAL $end
$var parameter 5 . SG_SCHOOL $end
$var parameter 2 / S_MAIN_GREEN $end
$var parameter 2 0 S_MAIN_YELLOW $end
$var parameter 2 1 S_SIDE_GREEN $end
$var parameter 2 2 S_SIDE_YELLOW $end
$var parameter 3 3 YELLOW $end
$var parameter 5 4 YLW_TICKS $end
$var reg 5 5 limit [4:0] $end
$var reg 3 6 main_light [2:0] $end
$var reg 3 7 side_light [2:0] $end
$var reg 2 8 state [1:0] $end
$var reg 5 9 timer [4:0] $end
$var reg 1 ! walk_light $end
$upscope $end
$upscope $end
$enddefinitions $end
$comment Show the parameter values. $end
$dumpall
b100 4
b10 3
b11 2
b10 1
b1 0
b0 /
b1110 .
b1010 -
b100 ,
b110 +
b101 *
b10100 )
b1 (
$end
#0
$dumpvars
b0 9
b0 8
b100 7
b1 6
b10100 5
0'
1&
0%
0$
b1 #
b100 "
0!
$end
#5000
1$
#10000
0$
#12000
0&
#15000
b1 9
1$
#20000
0$
#25000
b10 9
1$
#30000
0$
#35000
b11 9
1$
#40000
0$
#45000
b100 9
1$
#50000
0$
#55000
b101 9
1$
#60000
0$
#65000
b110 9
1$
#70000
0$
#75000
b111 9
1$
#80000
0$
#85000
b1000 9
1$
#90000
0$
#95000
b1001 9
1$
#100000
0$
#102000
b101 5
1%
#105000
b100 5
b10 #
b10 6
b1 8
b0 9
1$
#110000
0$
#115000
b1 9
1$
#120000
0$
#125000
b10 9
1$
#130000
0$
#135000
b11 9
1$
#140000
0$
#142000
0%
#145000
b1010 5
1!
b1 "
b1 7
b100 #
b100 6
b10 8
b0 9
1$
#150000
0$
#155000
b1 9
1$
#160000
0$
#165000
b10 9
1$
#170000
0$
#175000
b11 9
1$
#180000
0$
#185000
b100 9
1$
#190000
0$
#195000
b101 9
1$
#200000
0$
#205000
b110 9
1$
#210000
0$
#215000
b111 9
1$
#220000
0$
#225000
b1000 9
1$
#230000
0$
#235000
b1001 9
1$
#240000
0$
#242000
b10100 5
0!
b100 "
b100 7
b1 #
b1 6
b0 9
b0 8
1&
#245000
1$
#250000
0$
#252000
0&
#255000
b1 9
1$
#260000
0$
#265000
b10 9
1$
#270000
0$
#275000
b11 9
1$
#280000
0$
#285000
b100 9
1$
