CAPSTONE HDL/labs/lab10/traffic_light_controller.v
`timescale 1ns / 1ps

module traffic_light_controller (
    input  wire       clk,
    input  wire       reset,
    input  wire       ped_request,
    output reg  [2:0] main_light,
    output reg  [2:0] side_light,
    output reg        walk_light
);

    localparam [2:0] RED    = 3'b100,
                     YELLOW = 3'b010,
                     GREEN  = 3'b001;

    localparam [1:0] S_TRAIN_GO   = 2'b00,
                     S_TRAIN_WARN = 2'b01,
                     S_BOAT_GO    = 2'b10,
                     S_BOAT_WARN  = 2'b11;

    reg [1:0] state, next_state;
    reg [4:0] counter;
    reg       boat_latched;

    always @(posedge clk or posedge reset) begin
        if (reset) begin
            state        <= S_TRAIN_GO;
            counter      <= 5'd0;
            boat_latched <= 1'b0;
        end else begin
            state <= next_state;
            if (state != next_state) begin
                counter <= 5'd0;
            end else begin
                counter <= counter + 5'd1;
            end
            if (ped_request) begin
                boat_latched <= 1'b1;
            end else if (state == S_TRAIN_GO && next_state == S_TRAIN_WARN) begin
                boat_latched <= 1'b0;
            end
        end
    end

    always @(*) begin
        next_state = state;
        case (state)
            S_TRAIN_GO: begin
                if (boat_latched && (counter >= 5 - 1))
                    next_state = S_TRAIN_WARN;
                else if (!boat_latched && (counter >= 20 - 1))
                    next_state = S_TRAIN_WARN;
            end
            S_TRAIN_WARN: begin
                if (counter >= 4 - 1)
                    next_state = S_BOAT_GO;
            end
            S_BOAT_GO: begin
                if (counter >= 10 - 1)
                    next_state = S_BOAT_WARN;
            end
            S_BOAT_WARN: begin
                if (counter >= 4 - 1)
                    next_state = S_TRAIN_GO;
            end
        endcase
    end

    always @(*) begin
        main_light = RED;
        side_light = RED;
        walk_light = 1'b0;
        case (state)
            S_TRAIN_GO: begin
                main_light = GREEN;
                side_light = RED;
            end
            S_TRAIN_WARN: begin
                main_light = YELLOW;
                side_light = RED;
            end
            S_BOAT_GO: begin
                main_light = RED;
                side_light = GREEN;
                walk_light = 1'b1;
            end
            S_BOAT_WARN: begin
                main_light = RED;
                side_light = YELLOW;
                walk_light = 1'b1;
            end
        endcase
    end

endmodule

CAPSTONE HDL/labs/lab10/tb_traffic_light_controller.v
`timescale 1ns / 1ps

module tb_traffic_light_controller;

    reg        clk;
    reg        reset;
    reg        ped_request;
    wire [2:0] main_light;
    wire [2:0] side_light;
    wire       walk_light;

    traffic_light_controller uut (
        .clk         (clk),
        .reset       (reset),
        .ped_request (ped_request),
        .main_light  (main_light),
        .side_light  (side_light),
        .walk_light  (walk_light)
    );

    always #5 clk = ~clk;

    always @(posedge clk) begin
        $display("t=%0t state=%b counter=%0d latched=%b main=%b side=%b walk=%b ped=%b",
                  $time, uut.state, uut.counter, uut.boat_latched,
                  main_light, side_light, walk_light, ped_request);
    end

    initial begin
        $dumpfile("tb_traffic_light_controller.vcd");
        $dumpvars(0, tb_traffic_light_controller);

        clk = 0;
        reset = 1;
        ped_request = 0;
        #20 reset = 0;

        #380;

        #5  ped_request = 1;
        #10 ped_request = 0;

        #230;

        #60;

        $finish;
    end

endmodule

CAPSTONE HDL/labs/lab10/tb_traffic_light_controller.vcd
$date
	Tue Jul 21 11:00:37 2026
$end
$version
	Icarus Verilog
$end
$timescale
	1ps
$end
$scope module tb_traffic_light_controller $end
$var wire 1 ! walk_light $end
$var wire 3 " side_light [2:0] $end
$var wire 3 # main_light [2:0] $end
$var reg 1 $ clk $end
$var reg 1 % ped_request $end
$var reg 1 & reset $end
$scope module uut $end
$var wire 1 $ clk $end
$var wire 1 % ped_request $end
$var wire 1 & reset $end
$var parameter 3 ' GREEN $end
$var parameter 3 ( RED $end
$var parameter 2 ) S_BOAT_GO $end
$var parameter 2 * S_BOAT_WARN $end
$var parameter 2 + S_TRAIN_GO $end
$var parameter 2 , S_TRAIN_WARN $end
$var parameter 3 - YELLOW $end
$var reg 1 . boat_latched $end
$var reg 5 / counter [4:0] $end
$var reg 3 0 main_light [2:0] $end
$var reg 2 1 next_state [1:0] $end
$var reg 3 2 side_light [2:0] $end
$var reg 2 3 state [1:0] $end
$var reg 1 ! walk_light $end
$upscope $end
$upscope $end
$enddefinitions $end
$comment Show the parameter values. $end
$dumpall
b10 -
b1 ,
b0 +
b11 *
b10 )
b100 (
b1 '
$end
#0
$dumpvars
b0 3
b100 2
b0 1
b1 0
b0 /
0.
1&
0%
0$
b1 #
b100 "
0!
$end
#5000
1$
#10000
0$
#15000
1$
#20000
0$
0&
#25000
b1 /
1$
#30000
0$
#35000
b10 /
1$
#40000
0$
#45000
b11 /
1$
#50000
0$
#55000
b100 /
1$
#60000
0$
#65000
b101 /
1$
#70000
0$
#75000
b110 /
1$
#80000
0$
#85000
b111 /
1$
#90000
0$
#95000
b1000 /
1$
#100000
0$
#105000
b1001 /
1$
#110000
0$
#115000
b1010 /
1$
#120000
0$
#125000
b1011 /
1$
#130000
0$
#135000
b1100 /
1$
#140000
0$
#145000
b1101 /
1$
#150000
0$
#155000
b1110 /
1$
#160000
0$
#165000
b1111 /
1$
#170000
0$
#175000
b10000 /
1$
#180000
0$
#185000
b10001 /
1$
#190000
0$
#195000
b10010 /
1$
#200000
0$
#205000
b1 1
b10011 /
1$
#210000
0$
#215000
b10 #
b10 0
b0 /
b1 3
1$
#220000
0$
#225000
b1 /
1$
#230000
0$
#235000
b10 /
1$
#240000
0$
#245000
b10 1
b11 /
1$
#250000
0$
#255000
1!
b1 "
b1 2
b100 #
b100 0
b0 /
b10 3
1$
#260000
0$
#265000
b1 /
1$
#270000
0$
#275000
b10 /
1$
#280000
0$
#285000
b11 /
1$
#290000
0$
#295000
b100 /
1$
#300000
0$
#305000
b101 /
1$
#310000
0$
#315000
b110 /
1$
#320000
0$
#325000
b111 /
1$
#330000
0$
#335000
b1000 /
1$
#340000
0$
#345000
b11 1
b1001 /
1$
#350000
0$
#355000
1!
b10 "
b10 2
b0 /
b11 3
1$
#360000
0$
#365000
b1 /
1$
#370000
0$
#375000
b10 /
1$
#380000
0$
#385000
b0 1
b11 /
1$
#390000
0$
#395000
b1 #
b1 0
0!
b100 "
b100 2
b0 /
b0 3
1$
#400000
0$
#405000
1.
b1 /
1$
1%
#410000
0$
#415000
b10 /
1$
0%
#420000
0$
#425000
b11 /
1$
#430000
0$
#435000
b1 1
b100 /
1$
#440000
0$
#445000
b10 #
b10 0
0.
b0 /
b1 3
1$
#450000
0$
#455000
b1 /
1$
#460000
0$
#465000
b10 /
1$
#470000
0$
#475000
b10 1
b11 /
1$
#480000
0$
#485000
1!
b1 "
b1 2
b100 #
b100 0
b0 /
b10 3
1$
#490000
0$
#495000
b1 /
1$
#500000
0$
#505000
b10 /
1$
#510000
0$
#515000
b11 /
1$
#520000
0$
#525000
b100 /
1$
#530000
0$
#535000
b101 /
1$
#540000
0$
#545000
b110 /
1$
#550000
0$
#555000
b111 /
1$
#560000
0$
#565000
b1000 /
1$
#570000
0$
#575000
b11 1
b1001 /
1$
#580000
0$
#585000
1!
b10 "
b10 2
b0 /
b11 3
1$
#590000
0$
#595000
b1 /
1$
#600000
0$
#605000
b10 /
1$
#610000
0$
#615000
b0 1
b11 /
1$
#620000
0$
#625000
b1 #
b1 0
0!
b100 "
b100 2
b0 /
b0 3
1$
#630000
0$
#635000
b1 /
1$
#640000
0$
#645000
b10 /
1$
#650000
0$
#655000
b11 /
1$
#660000
0$
#665000
b100 /
1$
#670000
0$
#675000
b101 /
1$
#680000
0$
#685000
b110 /
1$
#690000
0$
#695000
b111 /
1$
#700000
0$
#705000
b1000 /
1$
