lab06/lab06/latch_flipflop.v
`timescale 1ns / 1ps

module d_latch(
    input d,
    input enable,
    output reg q_latch
);
    always @(*) begin
        if (enable) begin
            q_latch = d;
        end
    end
endmodule

module d_flip_flop(
    input d,
    input clk,
    input reset,
    output reg q
);
    always @(posedge clk) begin
        if (reset) begin
            q <= 1'b0;
        end else begin
            q <= d;
        end
    end
endmodule

module dff_async_reset(
    input d,
    input clk,
    input reset_n,
    output reg q_ff
);
    always @(posedge clk or negedge reset_n) begin
        if (!reset_n) begin
            q_ff <= 1'b0;
        end else begin
            q_ff <= d;
        end
    end
endmodule

lab06/lab06/tb_latch_flipflop.v
`timescale 1ns / 1ps

module tb_latch_flipflop;
    reg d;
    reg enable;
    reg clk;
    reg reset;
    reg reset_n;
    wire q_latch;
    wire q_ff_sync;
    wire q_ff_async;

    d_latch latch0 (.d(d), .enable(enable), .q_latch(q_latch));
    d_flip_flop ff0 (.d(d), .clk(clk), .reset(reset), .q(q_ff_sync));
    dff_async_reset ff1 (.d(d), .clk(clk), .reset_n(reset_n), .q_ff(q_ff_async));

    initial begin
        clk = 1'b0;
        forever #5 clk = ~clk;
    end

    initial begin
        $dumpfile("lab06_latch_flipflop.vcd");
        $dumpvars(0, tb_latch_flipflop);

        d       = 1'b0;
        enable  = 1'b0;
        reset   = 1'b1;
        reset_n = 1'b0;
        #12;

        reset   = 1'b0;
        reset_n = 1'b1;
        #10;

        enable = 1'b1;
        d = 1'b1;
        #12;

        enable = 1'b0;
        d = 1'b0;
        #10;

        enable = 1'b1;
        #14;

        d = 1'b1;
        #3;

        reset_n = 1'b0;
        #4;

        reset_n = 1'b1;
        #13;

        d = 1'b0;
        #10;

        d = 1'b1;
        #10;

        $finish;
    end
endmodule

lab06/lab06/lab06_latch_flipflop.vcd
$date
	Thu Jul 16 13:07:35 2026
$end
$version
	Icarus Verilog
$end
$timescale
	1ps
$end
$scope module tb_latch_flipflop $end
$var wire 1 ! q_latch $end
$var wire 1 " q_ff_sync $end
$var wire 1 # q_ff_async $end
$var reg 1 $ clk $end
$var reg 1 % d $end
$var reg 1 & enable $end
$var reg 1 ' reset $end
$var reg 1 ( reset_n $end
$scope module ff0 $end
$var wire 1 $ clk $end
$var wire 1 % d $end
$var wire 1 ' reset $end
$var reg 1 " q $end
$upscope $end
$scope module ff1 $end
$var wire 1 $ clk $end
$var wire 1 % d $end
$var wire 1 ( reset_n $end
$var reg 1 # q_ff $end
$upscope $end
$scope module latch0 $end
$var wire 1 % d $end
$var wire 1 & enable $end
$var reg 1 ! q_latch $end
$upscope $end
$upscope $end
$enddefinitions $end
$comment Show the parameter values. $end
$dumpall
$end
#0
$dumpvars
0(
1'
0&
0%
0$
0#
x"
x!
$end
#5000
0"
1$
#10000
0$
#12000
1(
0'
#15000
1$
#20000
0$
#22000
1!
1%
1&
#25000
1"
1#
1$
#30000
0$
#34000
0%
0&
#35000
0"
0#
1$
#40000
0$
#44000
0!
1&
#45000
1$
#50000
0$
#55000
1$
#58000
1!
1%
#60000
0$
#61000
0(
#65000
1"
1#
1(
1$
#70000
0$
#75000
1$
#78000
0!
0%
#80000
0$
#85000
0"
0#
1$
#88000
1!
1%
#90000
0$
#95000
1"
1#
1$
