lab08/lab08/shift_register.v
`timescale 1ns / 1ps

module shift_register4(
    input clk,
    input reset,
    input load,
    input direction,
    input serial_in,
    input [3:0] parallel_in,
    output reg [3:0] q,
    output serial_out
);
    assign serial_out = (direction) ? q[3] : q[0];

    always @(posedge clk) begin
        if (reset) begin
            q <= 4'b0000;
        end else if (load) begin
            q <= parallel_in;
        end else begin
            if (direction)
                q <= {q[2:0], serial_in};
            else
                q <= {serial_in, q[3:1]};
        end
    end
endmodule

lab08/lab08/tb_shift_register.v
`timescale 1ns / 1ps

module tb_shift_register;
    reg clk;
    reg reset;
    reg load;
    reg direction;
    reg serial_in;
    reg [3:0] parallel_in;
    wire [3:0] q;
    wire serial_out;

    shift_register4 uut (
        .clk(clk),
        .reset(reset),
        .load(load),
        .direction(direction),
        .serial_in(serial_in),
        .parallel_in(parallel_in),
        .q(q),
        .serial_out(serial_out)
    );

    initial begin
        clk = 1'b0;
        forever #5 clk = ~clk;
    end

    always @(posedge clk) begin
        $strobe("%0t\t %b\t %b\t %b\t %b\t %b\t\t %b\t %b\t %b",
                $time, clk, reset, load, direction, serial_in, parallel_in, q, serial_out);
    end

    initial begin
        $dumpfile("lab08_shift_register.vcd");
        $dumpvars(0, tb_shift_register);

        $display("");
        $display("               Lab 08 - Shift Register Testbench with Challenge");
        $display("           =======================================================");
        $display("");
        $display(" Time\tclk\trst\tload\tdirection\ts_in\tp_in\t q\ts_out");
        $display("---------------------------------------------------------------");

        clk = 1'b0;
        reset = 1'b1;
        load = 1'b0;
        direction = 1'b0;
        serial_in = 1'b0;
        parallel_in = 4'b1010;

        // --- 1. Synchronous Reset (first posedge at t=5) ---
        #10;
        reset = 1'b0;

        // --- 2. Parallel Load ---
        #10;
        load = 1'b1;
        #10;
        load = 1'b0;

        // --- 3. Shift Right (direction=0) with serial_in=1 ---
        serial_in = 1'b1;
        direction = 1'b0;
        #10;
        #10;
        #10;

        // --- 4. Load a distinct pattern for shift-left test ---
        load = 1'b1;
        parallel_in = 4'b0110;
        serial_in = 1'b0;
        #10;

        // --- 5. Shift Left (direction=1) with alternating serial_in ---
        load = 1'b0;
        direction = 1'b1;
        serial_in = 1'b0;
        #10;
        serial_in = 1'b1;
        #10;
        serial_in = 1'b0;
        #10;
        serial_in = 1'b1;
        #10;
        serial_in = 1'b0;
        #10;

        $finish;
    end
endmodule

lab08/lab08/lab08_shift_register.vcd
$date
	Thu Jul 16 15:29:09 2026
$end
$version
	Icarus Verilog
$end
$timescale
	1ps
$end
$scope module tb_shift_register $end
$var wire 1 ! serial_out $end
$var wire 4 " q [3:0] $end
$var reg 1 # clk $end
$var reg 1 $ direction $end
$var reg 1 % load $end
$var reg 4 & parallel_in [3:0] $end
$var reg 1 ' reset $end
$var reg 1 ( serial_in $end
$scope module uut $end
$var wire 1 # clk $end
$var wire 1 $ direction $end
$var wire 1 % load $end
$var wire 4 ) parallel_in [3:0] $end
$var wire 1 ' reset $end
$var wire 1 ( serial_in $end
$var wire 1 ! serial_out $end
$var reg 4 * q [3:0] $end
$upscope $end
$upscope $end
$enddefinitions $end
$comment Show the parameter values. $end
$dumpall
$end
#0
$dumpvars
bx *
b1010 )
0(
1'
b1010 &
0%
0$
0#
bx "
x!
$end
#5000
0!
b0 "
b0 *
1#
#10000
0#
0'
#15000
1#
#20000
0#
1%
#25000
b1010 "
b1010 *
1#
#30000
0#
1(
0%
#35000
1!
b1101 "
b1101 *
1#
#40000
0#
#45000
0!
b1110 "
b1110 *
1#
#50000
0#
#55000
1!
b1111 "
b1111 *
1#
#60000
0#
0(
b110 &
b110 )
1%
#65000
0!
b110 "
b110 *
1#
#70000
0#
1$
0%
#75000
1!
b1100 "
b1100 *
1#
#80000
0#
1(
#85000
b1001 "
b1001 *
1#
#90000
0#
0(
#95000
0!
b10 "
b10 *
1#
#100000
0#
1(
#105000
b101 "
b101 *
1#
#110000
0#
0(
#115000
1!
b1010 "
b1010 *
1#
