lab09/lab09/sequence_detector.v
`timescale 1ns / 1ps

module sequence_detector_1101(
    input clk,
    input reset,
    input bit_in,
    output reg detected
);
    localparam S0    = 3'd0;
    localparam S1    = 3'd1;
    localparam S11   = 3'd2;
    localparam S110  = 3'd3;
    localparam S1101 = 3'd4;

    reg [2:0] state;
    reg [2:0] next_state;

    always @(*) begin
        case (state)
            S0:    next_state = bit_in ? S1    : S0;
            S1:    next_state = bit_in ? S11   : S0;
            S11:   next_state = bit_in ? S11   : S110;
            S110:  next_state = bit_in ? S1101 : S0;
            S1101: next_state = bit_in ? S11   : S0;
            default: next_state = S0;
        endcase
    end

    always @(*) begin
        detected = (state == S1101);
    end

    always @(posedge clk) begin
        if (reset) begin
            state <= S0;
        end else begin
            state <= next_state;
        end
    end
endmodule

lab09/lab09/tb_sequence_detector.v
`timescale 1ns / 1ps

module tb_sequence_detector;
    reg clk;
    reg reset;
    reg bit_in;
    wire detected;

    reg [15:0] stream;
    integer i;

    sequence_detector_1101 uut (
        .clk(clk),
        .reset(reset),
        .bit_in(bit_in),
        .detected(detected)
    );

    initial begin
        clk = 1'b0;
        forever #5 clk = ~clk;
    end

    initial begin
        $dumpfile("lab09_sequence_detector.vcd");
        $dumpvars(0, tb_sequence_detector);

        $display("Time clk reset bit_in detected state next_state");
        $display("----------------------------------------------");

        reset = 1'b1;
        bit_in = 1'b0;
        stream = 16'b1101_1011_0110_1101;
        #12;
        reset = 1'b0;

        for (i = 15; i >= 0; i = i - 1) begin
            bit_in = stream[i];
            #10;
            $display("%4t  %b    %b     %b       %b       %d    %d",
                     $time, clk, reset, bit_in, detected, uut.state, uut.next_state);
        end

        $display("----------------------------------------------");
        $display("Simulation complete.");
        $finish;
    end
endmodule

lab09/lab09/lab09_sequence_detector.vcd
$date
	Thu Jul 16 16:40:11 2026
$end
$version
	Icarus Verilog
$end
$timescale
	1ps
$end
$scope module tb_sequence_detector $end
$var wire 1 ! detected $end
$var reg 1 " bit_in $end
$var reg 1 # clk $end
$var reg 1 $ reset $end
$var reg 16 % stream [15:0] $end
$var integer 32 & i [31:0] $end
$scope module uut $end
$var wire 1 " bit_in $end
$var wire 1 # clk $end
$var wire 1 $ reset $end
$var parameter 3 ' S0 $end
$var parameter 3 ( S1 $end
$var parameter 3 ) S11 $end
$var parameter 3 * S110 $end
$var parameter 3 + S1101 $end
$var reg 1 ! detected $end
$var reg 3 , next_state [2:0] $end
$var reg 3 - state [2:0] $end
$upscope $end
$upscope $end
$enddefinitions $end
$comment Show the parameter values. $end
$dumpall
b100 +
b11 *
b10 )
b1 (
b0 '
$end
#0
$dumpvars
bx -
b0 ,
bx &
b1101101101101101 %
1$
0#
0"
x!
$end
#5000
0!
b0 -
1#
#10000
0#
#12000
b1 ,
1"
b1111 &
0$
#15000
b10 ,
b1 -
1#
#20000
0#
#22000
b1110 &
#25000
b10 -
1#
#30000
0#
#32000
b11 ,
0"
b1101 &
#35000
b0 ,
b11 -
1#
#40000
0#
#42000
b100 ,
1"
b1100 &
#45000
1!
b10 ,
b100 -
1#
#50000
0#
#52000
b1011 &
#55000
0!
b10 -
1#
#60000
0#
#62000
b11 ,
0"
b1010 &
#65000
b0 ,
b11 -
1#
#70000
0#
#72000
b100 ,
1"
b1001 &
#75000
1!
b10 ,
b100 -
1#
#80000
0#
#82000
b1000 &
#85000
0!
b10 -
1#
#90000
0#
#92000
b11 ,
0"
b111 &
#95000
b0 ,
b11 -
1#
#100000
0#
#102000
b100 ,
1"
b110 &
#105000
1!
b10 ,
b100 -
1#
#110000
0#
#112000
b101 &
#115000
0!
b10 -
1#
#120000
0#
#122000
b11 ,
0"
b100 &
#125000
b0 ,
b11 -
1#
#130000
0#
#132000
b100 ,
1"
b11 &
#135000
1!
b10 ,
b100 -
1#
#140000
0#
#142000
b10 &
#145000
0!
b10 -
1#
#150000
0#
#152000
b11 ,
0"
b1 &
#155000
b0 ,
b11 -
1#
#160000
0#
#162000
b100 ,
1"
b0 &
#165000
1!
b10 ,
b100 -
1#
#170000
0#
#172000
b11111111111111111111111111111111 &
